cropduster/__init__.py
cropduster/exceptions.py
cropduster/fields.py
cropduster/files.py
cropduster/forms.py
cropduster/models.py
cropduster/resizing.py
cropduster/settings.py
cropduster/urls.py
cropduster/migrations/0001_initial.py
cropduster/migrations/0002_alt_text.py
cropduster/migrations/__init__.py
cropduster/standalone/__init__.py
cropduster/standalone/metadata.py
cropduster/standalone/models.py
cropduster/standalone/views.py
cropduster/standalone/static/ckeditor/ckeditor/plugins/cropduster/plugin.js
cropduster/standalone/static/ckeditor/ckeditor/plugins/cropduster/dialogs/cropduster.js
cropduster/standalone/static/ckeditor/ckeditor/plugins/cropduster/icons/cropduster.png
cropduster/standalone/static/ckeditor/ckeditor/plugins/cropduster/lang/en.js
cropduster/standalone/static/ckeditor/ckeditor-dev/plugins/cropduster/plugin.js
cropduster/standalone/static/ckeditor/ckeditor-dev/plugins/cropduster/dialogs/cropduster.js
cropduster/standalone/static/ckeditor/ckeditor-dev/plugins/cropduster/icons/cropduster.png
cropduster/standalone/static/ckeditor/ckeditor-dev/plugins/cropduster/lang/en.js
cropduster/static/cropduster/css/cropduster.css
cropduster/static/cropduster/css/jcrop.gif
cropduster/static/cropduster/css/jquery.jcrop.css
cropduster/static/cropduster/css/upload.css
cropduster/static/cropduster/img/arrows.png
cropduster/static/cropduster/img/blank.gif
cropduster/static/cropduster/img/cropduster_icon_upload_hover.png
cropduster/static/cropduster/img/cropduster_icon_upload_select.png
cropduster/static/cropduster/img/progressbar.gif
cropduster/static/cropduster/js/cropduster.js
cropduster/static/cropduster/js/jquery.class.js
cropduster/static/cropduster/js/jquery.form.js
cropduster/static/cropduster/js/jquery.jcrop.js
cropduster/static/cropduster/js/jquery.jcrop.min.js
cropduster/static/cropduster/js/json2.js
cropduster/static/cropduster/js/jsrender.js
cropduster/static/cropduster/js/upload.js
cropduster/templates/cropduster/custom_field.html
django_cropduster-4.15.0.dist-info/licenses/LICENSE
django_cropduster-4.15.0.dist-info/licenses/LICENSE.Jcrop.txt
django_cropduster-4.15.0.dist-info/METADATA
django_cropduster-4.15.0.dist-info/WHEEL
django_cropduster-4.15.0.dist-info/top_level.txt
django_cropduster-4.15.0.dist-info/RECORD
