Metadata-Version: 2.4
Name: django-cropduster
Version: 4.15.0
Summary: Django image uploader and cropping tool
Author-email: The Atlantic <programmers@theatlantic.com>
License: BSD-2-Clause
Project-URL: Homepage, https://github.com/theatlantic/django-cropduster
Project-URL: Issues, https://github.com/theatlantic/django-cropduster/issues
Classifier: Development Status :: 5 - Production/Stable
Classifier: Environment :: Web Environment
Classifier: Intended Audience :: Developers
Classifier: Natural Language :: English
Classifier: Operating System :: OS Independent
Classifier: Programming Language :: Python
Classifier: Programming Language :: Python :: 3
Classifier: Programming Language :: Python :: 3 :: Only
Classifier: Programming Language :: Python :: 3.8
Classifier: Programming Language :: Python :: 3.9
Classifier: Programming Language :: Python :: 3.10
Classifier: Programming Language :: Python :: 3.11
Classifier: Programming Language :: Python :: 3.12
Classifier: Programming Language :: Python :: 3.13
Classifier: Framework :: Django
Classifier: Framework :: Django :: 2.2
Classifier: Framework :: Django :: 3.2
Classifier: Framework :: Django :: 4.2
Classifier: Framework :: Django :: 5.0
Classifier: Framework :: Django :: 5.1
Classifier: Framework :: Django :: 5.2
Requires-Python: >=3.8
License-File: LICENSE
License-File: LICENSE.Jcrop.txt
Requires-Dist: Pillow
Requires-Dist: python-xmp-toolkit
Requires-Dist: django-generic-plus>=2.0.3
Dynamic: license-file
